nomad_projection/__init__.py
nomad_projection/neighbors.py
nomad_projection/projection.py
nomad_projection/figures/__init__.py
nomad_projection/figures/arxiv.py
nomad_projection/figures/eval.py
nomad_projection/figures/imagenet.py
nomad_projection/figures/pubmed.py
nomad_projection/figures/wiki.py
nomad_projection-0.0.1.dist-info/METADATA
nomad_projection-0.0.1.dist-info/WHEEL
nomad_projection-0.0.1.dist-info/top_level.txt
nomad_projection-0.0.1.dist-info/RECORD
